jinpy_utils/__init__.py
jinpy_utils/base/__init__.py
jinpy_utils/base/exceptions.py
jinpy_utils/cache/__init__.py
jinpy_utils/cache/backends.py
jinpy_utils/cache/config.py
jinpy_utils/cache/core.py
jinpy_utils/cache/enums.py
jinpy_utils/cache/exceptions.py
jinpy_utils/cache/interfaces.py
jinpy_utils/cache/utils.py
jinpy_utils/logger/__init__.py
jinpy_utils/logger/backends.py
jinpy_utils/logger/config.py
jinpy_utils/logger/core.py
jinpy_utils/logger/enums.py
jinpy_utils/logger/exceptions.py
jinpy_utils/py.typed
jinpy_utils/utils/__init__.py
jinpy_utils/utils/timing.py
jinpy_utils-0.2.0.dist-info/WHEEL
jinpy_utils-0.2.0.dist-info/METADATA
jinpy_utils-0.2.0.dist-info/RECORD
