Metadata-Version: 2.3
Name: jinpy-utils
Version: 0.2.0
Summary: jinpy-utils is a collection of minimal, type-safe Python utilities for Caching, Logging, Settings, and ORM. It follows modern Python practices (PEP 8, mypy, Ruff) and maintains high test coverage.
Keywords: python,utilities,caching,logging,settings,orm,asyncio
Author: Jinto A G
Author-email: Jinto A G <project.jintoag@gmail.com>
License: MIT
Classifier: Development Status :: 3 - Alpha
Classifier: Intended Audience :: Developers
Classifier: Topic :: Software Development :: Libraries
Classifier: Topic :: Utilities
Classifier: License :: OSI Approved :: MIT License
Classifier: Programming Language :: Python
Classifier: Programming Language :: Python :: 3
Classifier: Programming Language :: Python :: 3.12
Classifier: Programming Language :: Python :: 3.13
Classifier: Operating System :: OS Independent
Requires-Dist: aiofiles>=24.1.0
Requires-Dist: aiohttp>=3.12.15
Requires-Dist: alembic>=1.16.4
Requires-Dist: cachetools>=6.1.0
Requires-Dist: pydantic[email]>=2.11.7
Requires-Dist: python-dotenv>=1.1.1
Requires-Dist: redis>=6.4.0
Requires-Dist: sqlmodel>=0.0.24
Requires-Dist: structlog>=25.4.0
Requires-Dist: websockets>=15.0.1
Requires-Python: >=3.12.10
Project-URL: Homepage, https://github.com/jinto-ag/jinpy-utils
Project-URL: Issues, https://github.com/jinto-ag/jinpy-utils/issues
Project-URL: License, https://github.com/jinto-ag/jinpy-utils/blob/main/LICENSE
Project-URL: Repository, https://github.com/jinto-ag/jinpy-utils
